README.md
setup.py
plot_machine/__init__.py
plot_machine/characters.py
plot_machine/conflicts.py
plot_machine/masterplot.py
plot_machine/settings.py
plot_machine.egg-info/PKG-INFO
plot_machine.egg-info/SOURCES.txt
plot_machine.egg-info/dependency_links.txt
plot_machine.egg-info/requires.txt
plot_machine.egg-info/top_level.txt