Metadata-Version: 1.0
Name: plot-machine
Version: 0.1
Summary: A program to automate the algorithm described in William Wallace Cook's Plotto, The Masterbook of All Plots
Home-page: https://github.com/JarbasAl/plot_machine
Author: jarbasAI
Author-email: jarbasai@mailfence.com
License: MIT
Platform: UNKNOWN
